{
  "schema_version": 2,
  "repo": "c3",
  "branch": "issue-66-add-a-favicon-2215",
  "sha": "8a61ff1adced170d6c286377dc4c36cf15bf370b",
  "user": "unknown",
  "user_email": "arsilhavy@gmail.com",
  "timestamp": "2026-04-27T15:10:01Z",
  "phase": "all",
  "run_number": 1,
  "gate_name": null,
  "critic_verdict": "unknown",
  "critic_findings_count": 0,
  "critic_findings_by_rule": {},
  "critic_findings": [],
  "gates_first_pass": true,
  "gate_failures_after_critic": 0,
  "missed_gates": [],
  "gates_run": [
    "complexity",
    "coverage",
    "dead-code",
    "filesize",
    "gate-cache-stats",
    "issue-binding",
    "lint",
    "markdown",
    "plan",
    "pr-linkage",
    "quality-path-discipline",
    "review-coverage",
    "review",
    "skill-isolation",
    "test-quality",
    "tests",
    "work-structure-sync"
  ],
  "gates": {
    "complexity": {
      "status": "pass",
      "gate_timestamp": "2026-04-27T02:27:51Z",
      "files_checked": 1,
      "violations": 0,
      "violations_details": []
    },
    "coverage": {
      "status": "skip",
      "gate_timestamp": "2026-04-27T02:28:21Z",
      "coverage_tool": "js",
      "files_checked": 0,
      "below_threshold": 0,
      "below_threshold_details": []
    },
    "dead-code": {
      "status": "pass",
      "gate_timestamp": "2026-04-27T02:27:52Z",
      "files_checked": 1,
      "violations": 0,
      "violations_details": []
    },
    "filesize": {
      "status": "pass",
      "gate_timestamp": "2026-04-27T15:09:57Z",
      "files_checked": 2,
      "violations": 0,
      "violations_details": [],
      "duration_ms": 8000
    },
    "gate-cache-stats": {
      "status": "unknown"
    },
    "issue-binding": {
      "status": "pass",
      "gate_timestamp": "2026-04-27T15:09:58Z",
      "duration_ms": 1000
    },
    "lint": {
      "status": "pass",
      "gate_timestamp": "2026-04-27T02:27:58Z",
      "failures": 0,
      "failures_details": []
    },
    "markdown": {
      "status": "pass",
      "gate_timestamp": "2026-04-27T15:10:00Z",
      "duration_ms": 1000
    },
    "plan": {
      "status": "skip",
      "gate_timestamp": "2026-04-27T02:27:59Z"
    },
    "pr-linkage": {
      "status": "skip"
    },
    "quality-path-discipline": {
      "status": "pass",
      "gate_timestamp": "2026-04-27T15:09:59Z",
      "violations": 0,
      "violations_details": [],
      "duration_ms": 1000
    },
    "review-coverage": {
      "status": "complete",
      "gate_timestamp": "2026-04-27T15:09:49Z",
      "duration_ms": 105000
    },
    "review": {
      "status": "pass",
      "gate_timestamp": "2026-04-27T15:07:36Z",
      "duration_ms": 0
    },
    "skill-isolation": {
      "status": "pass",
      "gate_timestamp": "2026-04-27T15:09:59Z",
      "scanned_files": 0,
      "duration_ms": 0
    },
    "test-quality": {
      "status": "pass",
      "gate_timestamp": "2026-04-27T15:08:04Z",
      "scanned_files": 1,
      "violations": 0,
      "violations_details": [],
      "duration_ms": 28000
    },
    "tests": {
      "status": "pass",
      "gate_timestamp": "2026-04-27T15:08:04Z",
      "test_runner": "bin-test",
      "fingerprint": "45bdf0a090b0b3ecd03ad0f2fe225d21",
      "failed_subprojects": 0,
      "missing_tests": 0,
      "test_failures": 0,
      "failed_subprojects_details": [],
      "missing_tests_details": [],
      "test_failures_details": [],
      "duration_ms": 0
    },
    "work-structure-sync": {
      "status": "skip"
    }
  },
  "duration_seconds": 45729.0
}
