{
  "schema_version": 2,
  "repo": "lovitt-modern",
  "branch": "worktree-polymorphic-orbiting-dragon",
  "sha": "4a229ee8f5bcf39da3de78dbab2306057eb0a494",
  "user": "Jerrod Blavos",
  "user_email": "jblavos@arqu.co",
  "timestamp": "2026-05-03T22:17:07Z",
  "phase": "all",
  "run_number": 1,
  "gate_name": "complexity",
  "critic_verdict": "unknown",
  "critic_findings_count": 0,
  "critic_findings_by_rule": {},
  "critic_findings": [],
  "gates_first_pass": true,
  "gate_failures_after_critic": 0,
  "missed_gates": [],
  "gates_run": [
    "complexity"
  ],
  "gates": {
    "complexity": {
      "status": "pass",
      "gate_timestamp": "2026-05-03T22:17:06Z",
      "files_checked": 2,
      "violations": 0,
      "violations_details": [],
      "duration_ms": 0
    }
  },
  "duration_seconds": null
}
