{
  "schema_version": 2,
  "repo": "lovitt-modern",
  "branch": "worktree-polymorphic-orbiting-dragon",
  "sha": "8ef57977f0e395ea4feafa30946a92c04358fbb2",
  "user": "Jerrod Blavos",
  "user_email": "jblavos@arqu.co",
  "timestamp": "2026-05-04T10:06:48Z",
  "phase": "build",
  "run_number": 1,
  "gate_name": "filesize",
  "critic_verdict": "approved",
  "critic_findings_count": 0,
  "critic_findings_by_rule": {},
  "critic_findings": [],
  "gates_first_pass": false,
  "gate_failures_after_critic": 0,
  "missed_gates": [],
  "gates_run": [
    "filesize"
  ],
  "gates": {
    "filesize": {
      "status": "fail",
      "gate_timestamp": "2026-05-04T10:06:48Z",
      "files_checked": 5,
      "violations": 1,
      "violations_details": [
        {
          "file": "spec/models/product_variant_spec.rb",
          "lines": 381,
          "max": 300,
          "status": "fail"
        }
      ],
      "duration_ms": 0
    }
  },
  "duration_seconds": null
}
