{
  "schema_version": 1,
  "repo": "c3",
  "branch": "fix/connecting-ws-stale-clear-race",
  "sha": "6fcdd7d",
  "user": "unknown",
  "timestamp": "2026-04-20T20:11:02Z",
  "phase": "all",
  "run_number": 1,
  "gate_name": null,
  "critic_verdict": "unknown",
  "critic_findings_count": 0,
  "critic_findings_by_rule": {},
  "critic_findings": [],
  "gates_first_pass": true,
  "gate_failures_after_critic": 0,
  "missed_gates": [],
  "gates_run": [
    "complexity",
    "coverage",
    "dead-code",
    "design-audit",
    "filesize",
    "lint",
    "qa",
    "test-quality",
    "tests"
  ],
  "gates": {
    "complexity": {
      "status": "pass",
      "gate_timestamp": "2026-04-20T20:10:54Z",
      "files_checked": 2,
      "violations": 0,
      "violations_details": [],
      "duration_ms": 1000
    },
    "coverage": {
      "status": "pass",
      "gate_timestamp": "2026-04-20T20:11:01Z",
      "coverage_tool": "js",
      "below_threshold": 0,
      "below_threshold_details": [],
      "duration_ms": 1000
    },
    "dead-code": {
      "status": "pass",
      "gate_timestamp": "2026-04-20T20:10:54Z",
      "violations": 0,
      "violations_details": [],
      "duration_ms": 0
    },
    "design-audit": {
      "status": "pass",
      "gate_timestamp": "2026-04-20T20:09:39Z",
      "message": "Design audit not yet performed \u2014 run /rq:design-audit for UI audit",
      "overall_grade": "",
      "screenshots": 0,
      "screenshots_details": [],
      "categories": {},
      "duration_ms": 0
    },
    "filesize": {
      "status": "pass",
      "gate_timestamp": "2026-04-20T20:10:53Z",
      "files_checked": 2,
      "violations": 0,
      "violations_details": [],
      "duration_ms": 74000
    },
    "lint": {
      "status": "pass",
      "gate_timestamp": "2026-04-20T20:10:59Z",
      "failures": 0,
      "failures_details": [],
      "duration_ms": 5000
    },
    "qa": {
      "status": "pass",
      "gate_timestamp": "2026-04-20T20:09:39Z",
      "message": "QA testing not yet performed \u2014 run /rq:qa for browser testing",
      "flows_passed": 0,
      "flows_tested": 0,
      "flows_failed": 0,
      "issues": 0,
      "recordings": 0,
      "issues_details": [],
      "recordings_details": [],
      "duration_ms": 0
    },
    "test-quality": {
      "status": "pass",
      "gate_timestamp": "2026-04-20T20:11:01Z",
      "scanned_files": 1,
      "violations": 0,
      "violations_details": [],
      "duration_ms": 0
    },
    "tests": {
      "status": "pass",
      "gate_timestamp": "2026-04-20T20:11:00Z",
      "test_runner": "bin-test",
      "fingerprint": "b14b2edffe9a83ca47f5e326780edce3",
      "test_failures": 0,
      "failed_subprojects": 0,
      "missing_tests": 0,
      "test_failures_details": [],
      "failed_subprojects_details": [],
      "missing_tests_details": [],
      "duration_ms": 1000
    }
  },
  "duration_seconds": 82.0
}
