{
  "schema_version": 2,
  "repo": "doubtfire-client",
  "branch": "feat-deployme-document-drag-to-compose",
  "sha": "dab759a5d0bcf122052ccc7ecd0011154340d6fa",
  "user": "unknown",
  "user_email": "arsilhavy@gmail.com",
  "timestamp": "2026-04-26T18:03:50Z",
  "phase": "all",
  "run_number": 2,
  "gate_name": "issue-binding",
  "critic_verdict": "unknown",
  "critic_findings_count": 0,
  "critic_findings_by_rule": {},
  "critic_findings": [],
  "gates_first_pass": false,
  "gate_failures_after_critic": 0,
  "missed_gates": [],
  "gates_run": [
    "issue-binding"
  ],
  "gates": {
    "issue-binding": {
      "status": "fail",
      "gate_timestamp": "2026-04-26T18:03:49Z",
      "duration_ms": 0
    }
  },
  "duration_seconds": null
}
