{
  "schema_version": 2,
  "repo": "cortex",
  "branch": "issue-68-security-tie-sdk-bypasspermissions-to-manifest-2057",
  "sha": "4340275978c7012f43670d3ff5262c8996734fd5",
  "user": "Alicia Drinkwater",
  "user_email": "adrinkwater@arqu.co",
  "timestamp": "2026-04-30T19:24:53Z",
  "phase": "review",
  "run_number": 1,
  "gate_name": "quality-path-discipline",
  "critic_verdict": "unknown",
  "critic_findings_count": 0,
  "critic_findings_by_rule": {},
  "critic_findings": [],
  "gates_first_pass": true,
  "gate_failures_after_critic": 0,
  "missed_gates": [],
  "gates_run": [
    "quality-path-discipline"
  ],
  "gates": {
    "quality-path-discipline": {
      "status": "pass",
      "gate_timestamp": "2026-04-30T19:24:53Z",
      "violations": 0,
      "violations_details": [],
      "duration_ms": 0
    }
  },
  "duration_seconds": null
}
