{
  "schema_version": 1,
  "repo": "risklab-python",
  "branch": "feat/semantic-release",
  "sha": "6c04dbe4e",
  "user": "Jerrod Blavos",
  "timestamp": "2026-03-25T15:42:14Z",
  "phase": "all",
  "run_number": 1,
  "gate_name": "dead-code",
  "critic_verdict": "unknown",
  "critic_findings_count": 0,
  "critic_findings_by_rule": {},
  "critic_findings": [],
  "gates_first_pass": false,
  "gate_failures_after_critic": 0,
  "missed_gates": [],
  "gates_run": [
    "dead-code"
  ],
  "gates": {
    "dead-code": {
      "status": "fail",
      "gate_timestamp": "2026-03-25T15:42:13Z",
      "violations": 1,
      "violations_details": [
        {
          "type": "unused_import",
          "file": "backend/alembic/versions/20260325_1004_add_viewer_token_to_portal_uploads.py",
          "name": "sqlalchemy",
          "line": 12
        }
      ],
      "duration_ms": 0
    }
  },
  "duration_seconds": null
}
