{
  "schema_version": 2,
  "repo": "risklab",
  "branch": "audit-1295-pii-strip",
  "sha": "8c53916bfd86e8e0b1670df19726b6f9c1964d7a",
  "user": "Jonathan Thom",
  "user_email": "jthom@arqu.co",
  "timestamp": "2026-04-20T22:18:56Z",
  "phase": "all",
  "run_number": 2,
  "gate_name": "review",
  "critic_verdict": "approved",
  "critic_findings_count": 0,
  "critic_findings_by_rule": {},
  "critic_findings": [],
  "gates_first_pass": false,
  "gate_failures_after_critic": 0,
  "missed_gates": [],
  "gates_run": [
    "review"
  ],
  "gates": {
    "review": {
      "status": "fail",
      "gate_timestamp": "2026-04-20T22:18:56Z",
      "duration_ms": 0
    }
  },
  "duration_seconds": null
}
